CalculadoraAlexei/CalculadoraAlexei.py
CalculadoraAlexei/__init__.py
calculadoraalexei-0.0.1.dist-info/METADATA
calculadoraalexei-0.0.1.dist-info/WHEEL
calculadoraalexei-0.0.1.dist-info/licenses/LICENSE
calculadoraalexei-0.0.1.dist-info/RECORD
