Metadata-Version: 2.4
Name: CalculadoraAlexei
Version: 0.0.1
Summary: Calculadora desarrollada con el patron de diseño State.
Author-email: Alexei Duran <nadurana@udistrital.edu.co>
License: Copyright (c) 2025 Nicolas Alexei Duran Amariles
License-File: LICENSE
Keywords: calculadora,matematicas,pypi
Classifier: License :: OSI Approved :: MIT License
Classifier: Operating System :: OS Independent
Classifier: Programming Language :: Python :: 3
Requires-Python: >=3.8
